beachwatch/__init__.py
beachwatch/beachwatch.py
beachwatch-0.1.4.dist-info/LICENSE
beachwatch-0.1.4.dist-info/METADATA
beachwatch-0.1.4.dist-info/WHEEL
beachwatch-0.1.4.dist-info/top_level.txt
beachwatch-0.1.4.dist-info/RECORD
