Metadata-Version: 2.1
Name: beachwatch
Version: 0.1.4
Summary: A Python wrapper for the NSW Government's Beachwatch API.
Author-email: Ben Nour <hello@ben-nour.com>
License: MIT License
Project-URL: homepage, https://github.com/ben-n93/beachwatch
Project-URL: repository, https://github.com/ben-n93/beachwatch
Classifier: License :: OSI Approved :: MIT License
Classifier: Programming Language :: Python :: 3
Classifier: Programming Language :: Python :: 3.8
Classifier: Programming Language :: Python :: 3.9
Classifier: Programming Language :: Python :: 3.10
Classifier: Programming Language :: Python :: 3.11
Classifier: Programming Language :: Python :: 3.12
Requires-Python: >=3.8
License-File: LICENSE
Requires-Dist: requests~=2.32.3
Requires-Dist: python-dateutil==2.9.0.post0
